sqliteorm/__init__.py
sqliteorm/filters.py
sqliteorm/enums/filters.py
sqliteorm/models/fileds.py
sqliteorm/models/table.py
sqlitesimpleorm-0.2.4.dist-info/licenses/LICENSE
sqlitesimpleorm-0.2.4.dist-info/METADATA
sqlitesimpleorm-0.2.4.dist-info/WHEEL
sqlitesimpleorm-0.2.4.dist-info/top_level.txt
sqlitesimpleorm-0.2.4.dist-info/RECORD
