Metadata-Version: 2.4
Name: sqlitesimpleorm
Version: 0.2.4
Summary: SQLite3 simple ORM
Author-email: MistakeTZ <mistaketz@gmail.com>
License: MIT License
Requires-Python: >=3.8
License-File: LICENSE
Dynamic: license-file
